GeneralizedLogGamma/__init__.py
GeneralizedLogGamma/csh.py
GeneralizedLogGamma/dglg.py
GeneralizedLogGamma/entropy.py
GeneralizedLogGamma/loglik.py
GeneralizedLogGamma/moments.py
GeneralizedLogGamma/rglg.py
GeneralizedLogGamma-0.0.16.dist-info/LICENSE.txt
GeneralizedLogGamma-0.0.16.dist-info/METADATA
GeneralizedLogGamma-0.0.16.dist-info/WHEEL
GeneralizedLogGamma-0.0.16.dist-info/top_level.txt
GeneralizedLogGamma-0.0.16.dist-info/RECORD
