Metadata-Version: 2.1
Name: GeneralizedLogGamma
Version: 0.0.16
Summary: To fit, validate, diagnostic, and plot generalized gamma and log-gamma distributions.
Author-email: Carlos Alberto Cardozo Delgado <cardozopypackages@gmail.com>
Project-URL: Homepage, https://github.com
Project-URL: Bug Tracker, https://github.com
Keywords: statistics,data science,research
Classifier: Programming Language :: Python :: 3
Classifier: License :: OSI Approved :: MIT License
Classifier: Operating System :: OS Independent
Classifier: Topic :: Education
Classifier: Topic :: Scientific/Engineering
Classifier: Topic :: Scientific/Engineering :: Mathematics
Requires-Python: >=3.7
License-File: LICENSE.txt
